subtitle/__init__.py
subtitle/config.py
subtitle/http_dns.py
subtitle/main.py
subtitle/subtitle_downloader.py
subtitle-2.3.dist-info/METADATA
subtitle-2.3.dist-info/WHEEL
subtitle-2.3.dist-info/entry_points.txt
subtitle-2.3.dist-info/top_level.txt
subtitle-2.3.dist-info/RECORD
