Metadata-Version: 2.1
Name: subtitle
Version: 2.3
Summary: A cli tool to download subtitles.
Home-page: https://github.com/ihciah/subtitle
Author: ihciah
Author-email: ihciah@gmail.com
License: MIT License
Keywords: subtitle,downloader
Platform: UNKNOWN
Classifier: Development Status :: 4 - Beta
Classifier: Intended Audience :: Other Audience
Classifier: Natural Language :: Chinese (Traditional)
Classifier: License :: OSI Approved :: MIT License
Classifier: Programming Language :: Python
Classifier: Programming Language :: Python :: 2.6
Classifier: Programming Language :: Python :: 2.7
Classifier: Programming Language :: Python :: 3
Classifier: Programming Language :: Python :: 3.3
Classifier: Programming Language :: Python :: 3.4
Classifier: Programming Language :: Python :: 3.6
Classifier: Programming Language :: Python :: 3.7
Classifier: Programming Language :: Python :: 3.8
Classifier: Programming Language :: Python :: 3.9
Classifier: Programming Language :: Python :: Implementation :: CPython
Classifier: Programming Language :: Python :: Implementation :: PyPy
Requires-Dist: requests (>=2.17)
Requires-Dist: urllib3 (>=1.23)
